CHANGES.rst
MANIFEST.in
README.rst
setup.cfg
setup.py
jquery/__init__.py
jquery.pyproxy.egg-info/PKG-INFO
jquery.pyproxy.egg-info/SOURCES.txt
jquery.pyproxy.egg-info/dependency_links.txt
jquery.pyproxy.egg-info/entry_points.txt
jquery.pyproxy.egg-info/namespace_packages.txt
jquery.pyproxy.egg-info/not-zip-safe
jquery.pyproxy.egg-info/requires.txt
jquery.pyproxy.egg-info/top_level.txt
jquery/pyproxy/ROADMAP.rst
jquery/pyproxy/__init__.py
jquery/pyproxy/base.py
jquery/pyproxy/configure.zcml
jquery/pyproxy/jq_django.py
jquery/pyproxy/migration.py
jquery/pyproxy/models.py
jquery/pyproxy/plone.py
jquery/pyproxy/tests.zcml
jquery/pyproxy/utils.py
jquery/pyproxy/version.txt
jquery/pyproxy/media/jquery.pyproxy.js
jquery/pyproxy/media/jquery.pyproxy.min.js
jquery/pyproxy/media/jquery.pyproxy.spinner.css
jquery/pyproxy/media/jquery.pyproxy.spinner.js
jquery/pyproxy/media/jquery.pyproxy.spinner.min.js
jquery/pyproxy/plugins/__init__.py
jquery/pyproxy/plugins/jq_effects.py
jquery/pyproxy/plugins/jq_manipulation.py
jquery/pyproxy/plugins/jq_traverse.py
jquery/pyproxy/plugins/wrong_plugin.py
jquery/pyproxy/profiles/default/cssregistry.xml
jquery/pyproxy/profiles/default/jsregistry.xml
jquery/pyproxy/profiles/default/metadata.xml
jquery/pyproxy/profiles/default/skins.xml
jquery/pyproxy/profiles/tests/skins.xml
jquery/pyproxy/samples/__init__.py
jquery/pyproxy/samples/common.py
jquery/pyproxy/samples/django/__init__.py
jquery/pyproxy/samples/django/ajax.py
jquery/pyproxy/samples/plone/__init__.py
jquery/pyproxy/samples/plone/ajax.py
jquery/pyproxy/samples/plone/configure.zcml
jquery/pyproxy/samples/plone/sample_page.pt
jquery/pyproxy/samples/simple_html/add_item.json
jquery/pyproxy/samples/simple_html/index.html
jquery/pyproxy/samples/simple_html/toggle_item.json
jquery/pyproxy/skins/pyproxy/pyproxy_spinner.gif
jquery/pyproxy/skins/pyproxy_tests/pyproxy_json_test1.pt
jquery/pyproxy/skins/pyproxy_tests/pyproxy_json_test2.pt
jquery/pyproxy/skins/pyproxy_tests/pyproxy_tests.js
jquery/pyproxy/skins/pyproxy_tests/pyproxy_tests.pt
jquery/pyproxy/skins/pyproxy_tests/qunit.css
jquery/pyproxy/skins/pyproxy_tests/qunit.js
jquery/pyproxy/tests/__init__.py
jquery/pyproxy/tests/django.txt
jquery/pyproxy/tests/django_tests.py
jquery/pyproxy/tests/plone.txt
jquery/pyproxy/tests/test_plone.py