Metadata-Version: 1.1
Name: jquery.pyproxy
Version: 0.5
Summary: A simple python egg and jquery plugin to easily use JQuery in Django/Plone/.. websites.
Home-page: http://github.com/zestsoftware/jquery.pyproxy
Author: Vincent Pretre
Author-email: vincent.pretre@gmail.com
License: GPL
Keywords: jquery python proxy
Platform: UNKNOWN
Classifier: Framework :: Plone
Classifier: Framework :: Plone :: 3.3
Classifier: Framework :: Plone :: 4.0
Classifier: Framework :: Plone :: 4.1
Classifier: Framework :: Plone :: 4.2
Classifier: Framework :: Plone :: 4.3
Classifier: Framework :: Django
Classifier: Programming Language :: Python
Classifier: Programming Language :: Python :: 2.4
Classifier: Programming Language :: Python :: 2.5
Classifier: Programming Language :: Python :: 2.6
Classifier: Programming Language :: Python :: 2.7
